pipeline_sdk_test63/__init__.py
pipeline_sdk_test63/auth_service.py
pipeline_sdk_test63/inference_pipeline.py
pipeline_sdk_test63/model_inference_dsl_component.py
pipeline_sdk_test63/model_train_dsl_component.py
pipeline_sdk_test63/model_validate_dsl_component.py
pipeline_sdk_test63/pipeline_util.py
pipeline_sdk_test63/run_inference_pipeline.py
pipeline_sdk_test63/run_training_pipeline.py
pipeline_sdk_test63/run_validate_pipeline.py
pipeline_sdk_test63/train_pipeline.py
pipeline_sdk_test63/validate_pipeline.py
pipeline_sdk_test63-1.0.0.dist-info/METADATA
pipeline_sdk_test63-1.0.0.dist-info/WHEEL
pipeline_sdk_test63-1.0.0.dist-info/top_level.txt
pipeline_sdk_test63-1.0.0.dist-info/RECORD
